LICENSE
README.md
setup.py
pydate/__init__.py
pydate/pydate.py
pydate.egg-info/PKG-INFO
pydate.egg-info/SOURCES.txt
pydate.egg-info/dependency_links.txt
pydate.egg-info/top_level.txt