Metadata-Version: 2.1
Name: pydate
Version: 1.2.0
Summary: Python package made to set, parse, & format DateTime objects.
Home-page: https://github.com/CodeConfidant/pydate-time
Author: Drew Hainer
Author-email: codeconfidant@gmail.com
License: MIT
Platform: Windows
Platform: Linux
Requires-Python: >=3.6
License-File: LICENSE
